python_obs/__init__.py
python_obs/client.py
python_obs/clients.py
python_obs/exceptions.py
python_obs/scene.py
python_obs/source.py
python_obs/sync_utils.py
python_obs-1.3.0.dist-info/licenses/LICENSE
python_obs-1.3.0.dist-info/METADATA
python_obs-1.3.0.dist-info/WHEEL
python_obs-1.3.0.dist-info/top_level.txt
python_obs-1.3.0.dist-info/RECORD
