Metadata-Version: 2.4
Name: python_obs
Version: 1.3.0
Summary: A Python package for interacting with OBS Studio.
Author-email: Samuel Chichester <samuelchichester05@gmail.com>
License: MIT License
Project-URL: Homepage, https://github.com/SamChichester/PY-OBS
Classifier: Programming Language :: Python :: 3
Classifier: License :: OSI Approved :: MIT License
Classifier: Operating System :: OS Independent
License-File: LICENSE
Requires-Dist: websockets
Dynamic: license-file
